hellocry/__init__.py
hellocry/hellocry.py
hellocry-0.0.1.dist-info/METADATA
hellocry-0.0.1.dist-info/WHEEL
hellocry-0.0.1.dist-info/top_level.txt
hellocry-0.0.1.dist-info/RECORD
