Metadata-Version: 2.1
Name: hellocry
Version: 0.0.1
Summary: Test for crystal repository
Home-page: UNKNOWN
Author: Alessandro Cossard
Author-email: <alessandro.cossard@unito.it>
License: UNKNOWN
Keywords: python,video,stream,video stream,camera stream,sockets
Platform: UNKNOWN
Classifier: Development Status :: 1 - Planning
Classifier: Intended Audience :: Developers
Classifier: Programming Language :: Python :: 3
Classifier: Operating System :: Unix
Classifier: Operating System :: MacOS :: MacOS X
Classifier: Operating System :: Microsoft :: Windows
